scida/__init__.py
scida/config.py
scida/configfiles/__init__.py
scida/configfiles/config.yaml
scida/configfiles/simulations.yaml
scida/configfiles/units/__init__.py
scida/configfiles/units/auriga.yaml
scida/configfiles/units/eagle.yaml
scida/configfiles/units/erosita_events.yaml
scida/configfiles/units/flamingo.yaml
scida/configfiles/units/gadget_base.yaml
scida/configfiles/units/gadget_cosmological.yaml
scida/configfiles/units/gaia.yaml
scida/configfiles/units/general.yaml
scida/configfiles/units/gizmo.yaml
scida/configfiles/units/illustris.yaml
scida/configfiles/units/lgalaxies.yaml
scida/configfiles/units/mtng.yaml
scida/configfiles/units/rockstar.yaml
scida/convenience.py
scida/customs/__init__.py
scida/customs/arepo/MTNG/__init__.py
scida/customs/arepo/MTNG/dataset.py
scida/customs/arepo/TNGcluster/__init__.py
scida/customs/arepo/TNGcluster/dataset.py
scida/customs/arepo/__init__.py
scida/customs/arepo/dataset.py
scida/customs/arepo/extra_fields.py
scida/customs/arepo/helpers.py
scida/customs/arepo/selector.py
scida/customs/arepo/series.py
scida/customs/gadgetstyle/__init__.py
scida/customs/gadgetstyle/dataset.py
scida/customs/gadgetstyle/series.py
scida/customs/gizmo/dataset.py
scida/customs/gizmo/series.py
scida/customs/rockstar/dataset.py
scida/customs/swift/dataset.py
scida/customs/swift/series.py
scida/discovertypes.py
scida/fields.py
scida/helpers_hdf5.py
scida/helpers_misc.py
scida/interface.py
scida/interfaces/mixins/__init__.py
scida/interfaces/mixins/base.py
scida/interfaces/mixins/cosmology.py
scida/interfaces/mixins/spatial.py
scida/interfaces/mixins/units.py
scida/io/__init__.py
scida/io/_base.py
scida/io/fits.py
scida/misc.py
scida/registries.py
scida/series.py
scida/utilities.py
scida-0.3.5.dist-info/LICENSE
scida-0.3.5.dist-info/METADATA
scida-0.3.5.dist-info/WHEEL
scida-0.3.5.dist-info/RECORD
