Metadata-Version: 2.1
Name: scida
Version: 0.3.5
Summary: Convenience wrapper around large scientific datasets to process with dask.
Author: Chris Byrohl
Requires-Python: >=3.9,<4.0
Classifier: Programming Language :: Python :: 3
Classifier: Programming Language :: Python :: 3.9
Classifier: Programming Language :: Python :: 3.10
Classifier: Programming Language :: Python :: 3.11
Classifier: Programming Language :: Python :: 3.12
Requires-Dist: astropy (>=5.0)
Requires-Dist: dask[array,dataframe,distributed] (>=2023) ; python_full_version < "3.11.9"
Requires-Dist: dask[array,dataframe,distributed] (>=2024.4.1) ; python_full_version >= "3.11.9"
Requires-Dist: distributed (>=2023)
Requires-Dist: h5py (>=3.7.0,<4.0.0)
Requires-Dist: jupyter (>=1.0.0,<2.0.0)
Requires-Dist: numba (>=0.57)
Requires-Dist: numpy (>=1.21,<2.0) ; python_version < "3.11"
Requires-Dist: numpy (>=1.26) ; python_version >= "3.11"
Requires-Dist: pint (>=0.24,<0.25)
Requires-Dist: pyyaml (>=5.3.1)
Requires-Dist: requests (>=2.31.0,<3.0.0)
Requires-Dist: tqdm (>=4.64.1,<5.0.0)
Requires-Dist: zarr (>=v2.10.0,<3.0.0)
